deepbgc/__init__.py
deepbgc/__version__.py
deepbgc/data.py
deepbgc/features.py
deepbgc/main.py
deepbgc/util.py
deepbgc/command/__init__.py
deepbgc/command/base.py
deepbgc/command/download.py
deepbgc/command/info.py
deepbgc/command/pipeline.py
deepbgc/command/prepare.py
deepbgc/command/train.py
deepbgc/models/__init__.py
deepbgc/models/hmm.py
deepbgc/models/random_forest.py
deepbgc/models/rnn.py
deepbgc/models/wrapper.py
deepbgc/output/__init__.py
deepbgc/output/antismash_json.py
deepbgc/output/bgc_genbank.py
deepbgc/output/cluster_tsv.py
deepbgc/output/genbank.py
deepbgc/output/pfam_tsv.py
deepbgc/output/readme.py
deepbgc/output/writer.py
deepbgc/output/evaluation/__init__.py
deepbgc/output/evaluation/bgc_region_plot.py
deepbgc/output/evaluation/pfam_score_plot.py
deepbgc/output/evaluation/pr_plot.py
deepbgc/output/evaluation/roc_plot.py
deepbgc/pipeline/__init__.py
deepbgc/pipeline/annotator.py
deepbgc/pipeline/classifier.py
deepbgc/pipeline/detector.py
deepbgc/pipeline/pfam.py
deepbgc/pipeline/protein.py
deepbgc/pipeline/step.py
deepbgc-0.1.31.dist-info/LICENSE
deepbgc-0.1.31.dist-info/LICENSES_THIRD_PARTY
deepbgc-0.1.31.dist-info/METADATA
deepbgc-0.1.31.dist-info/WHEEL
deepbgc-0.1.31.dist-info/entry_points.txt
deepbgc-0.1.31.dist-info/top_level.txt
deepbgc-0.1.31.dist-info/RECORD
