Metadata-Version: 2.1
Name: deepbgc
Version: 0.1.31
Summary: DeepBGC - Biosynthetic Gene Cluster detection and classification
Home-page: https://github.com/Merck/DeepBGC
Author: David Příhoda, Geoffrey Hannigan
Author-email: david.prihoda1@merck.com
License: MIT
Keywords: biosynthetic gene clusters,bgc detection,deep learning,pfam2vec
Classifier: Development Status :: 4 - Beta
Classifier: Programming Language :: Python :: 3
Requires-Python: >=3.6,<3.8
License-File: LICENSE
License-File: LICENSES_THIRD_PARTY
Requires-Dist: argparse
Requires-Dist: biopython (>=1.78)
Requires-Dist: scikit-learn (==0.21.3)
Requires-Dist: pandas (==0.24.1)
Requires-Dist: numpy (==1.16.1)
Requires-Dist: keras (==2.2.4)
Requires-Dist: tensorflow (==1.15.4)
Requires-Dist: matplotlib (==2.2.3)
Requires-Dist: appdirs (>=1.4.3)
Requires-Dist: scipy (==1.2.0)
Requires-Dist: protobuf (<4)
Provides-Extra: hmm
Requires-Dist: hmmlearn (<0.2.7,>=0.2.1) ; extra == 'hmm'
